ragversion/__init__.py
ragversion/cli.py
ragversion/config.py
ragversion/detector.py
ragversion/exceptions.py
ragversion/models.py
ragversion/quick_start.py
ragversion/tracker.py
ragversion/watcher.py
ragversion/api/__init__.py
ragversion/api/app.py
ragversion/api/config.py
ragversion/api/dependencies.py
ragversion/api/models.py
ragversion/api/routes/__init__.py
ragversion/api/routes/documents.py
ragversion/api/routes/statistics.py
ragversion/api/routes/tracking.py
ragversion/api/routes/versions.py
ragversion/chunking/__init__.py
ragversion/chunking/detector.py
ragversion/chunking/splitters.py
ragversion/integrations/__init__.py
ragversion/integrations/langchain.py
ragversion/integrations/llamaindex.py
ragversion/integrations/langchain/__init__.py
ragversion/integrations/langchain/loader.py
ragversion/integrations/langchain/quick_start.py
ragversion/integrations/langchain/sync.py
ragversion/integrations/llamaindex/__init__.py
ragversion/integrations/llamaindex/loader.py
ragversion/integrations/llamaindex/quick_start.py
ragversion/integrations/llamaindex/sync.py
ragversion/notifications/__init__.py
ragversion/notifications/base.py
ragversion/notifications/discord.py
ragversion/notifications/email.py
ragversion/notifications/manager.py
ragversion/notifications/slack.py
ragversion/notifications/webhook.py
ragversion/parsers/__init__.py
ragversion/parsers/base.py
ragversion/parsers/docx.py
ragversion/parsers/markdown.py
ragversion/parsers/pdf.py
ragversion/parsers/text.py
ragversion/storage/__init__.py
ragversion/storage/base.py
ragversion/storage/sqlite.py
ragversion/storage/supabase.py
ragversion/storage/migrations/001_initial_schema.sql
ragversion/storage/migrations/002_chunk_versioning.sql
ragversion/testing/__init__.py
ragversion/testing/fixtures.py
ragversion/testing/mock_storage.py
ragversion/web/__init__.py
ragversion/web/routes.py
ragversion/web/templates/base.html
ragversion/web/templates/dashboard.html
ragversion/web/templates/diff.html
ragversion-0.11.0.dist-info/METADATA
ragversion-0.11.0.dist-info/WHEEL
ragversion-0.11.0.dist-info/entry_points.txt
ragversion-0.11.0.dist-info/licenses/LICENSE
ragversion-0.11.0.dist-info/RECORD
