Metadata-Version: 2.4
Name: ragversion
Version: 0.11.0
Summary: Async-first version tracking system for RAG applications
Project-URL: Homepage, https://github.com/sourangshupal/ragversion
Project-URL: Repository, https://github.com/sourangshupal/ragversion
Project-URL: Issues, https://github.com/sourangshupal/ragversion/issues
Author-email: Sourangshu Pal <paulbindass@gmail.com>
License: MIT
License-File: LICENSE
Keywords: document-tracking,langchain,llamaindex,rag,version-control
Classifier: Development Status :: 3 - Alpha
Classifier: Intended Audience :: Developers
Classifier: License :: OSI Approved :: MIT License
Classifier: Programming Language :: Python :: 3
Classifier: Programming Language :: Python :: 3.9
Classifier: Programming Language :: Python :: 3.10
Classifier: Programming Language :: Python :: 3.11
Classifier: Programming Language :: Python :: 3.12
Classifier: Topic :: Scientific/Engineering :: Artificial Intelligence
Classifier: Topic :: Software Development :: Libraries :: Python Modules
Requires-Python: >=3.9
Requires-Dist: aiofiles>=23.0.0
Requires-Dist: aiosqlite>=0.19.0
Requires-Dist: click>=8.1.0
Requires-Dist: httpx>=0.25.0
Requires-Dist: pydantic-settings>=2.0.0
Requires-Dist: pydantic>=2.0.0
Requires-Dist: python-dotenv>=1.0.0
Requires-Dist: python-magic>=0.4.27
Requires-Dist: pyyaml>=6.0
Requires-Dist: supabase>=2.0.0
Requires-Dist: watchdog>=3.0.0
Provides-Extra: all
Requires-Dist: black>=23.0.0; extra == 'all'
Requires-Dist: fastapi>=0.109.0; extra == 'all'
Requires-Dist: jinja2>=3.1.0; extra == 'all'
Requires-Dist: langchain-community>=0.0.1; extra == 'all'
Requires-Dist: langchain>=0.1.0; extra == 'all'
Requires-Dist: llama-index>=0.9.0; extra == 'all'
Requires-Dist: markdown>=3.5.0; extra == 'all'
Requires-Dist: mypy>=1.7.0; extra == 'all'
Requires-Dist: openpyxl>=3.1.0; extra == 'all'
Requires-Dist: pre-commit>=3.5.0; extra == 'all'
Requires-Dist: pypdf>=3.0.0; extra == 'all'
Requires-Dist: pytest-asyncio>=0.21.0; extra == 'all'
Requires-Dist: pytest-cov>=4.1.0; extra == 'all'
Requires-Dist: pytest>=7.4.0; extra == 'all'
Requires-Dist: python-docx>=1.0.0; extra == 'all'
Requires-Dist: python-pptx>=0.6.21; extra == 'all'
Requires-Dist: ruff>=0.1.0; extra == 'all'
Requires-Dist: uvicorn[standard]>=0.27.0; extra == 'all'
Provides-Extra: api
Requires-Dist: fastapi>=0.109.0; extra == 'api'
Requires-Dist: jinja2>=3.1.0; extra == 'api'
Requires-Dist: uvicorn[standard]>=0.27.0; extra == 'api'
Provides-Extra: dev
Requires-Dist: black>=23.0.0; extra == 'dev'
Requires-Dist: mypy>=1.7.0; extra == 'dev'
Requires-Dist: pre-commit>=3.5.0; extra == 'dev'
Requires-Dist: pytest-asyncio>=0.21.0; extra == 'dev'
Requires-Dist: pytest-cov>=4.1.0; extra == 'dev'
Requires-Dist: pytest>=7.4.0; extra == 'dev'
Requires-Dist: ruff>=0.1.0; extra == 'dev'
Provides-Extra: langchain
Requires-Dist: langchain-community>=0.0.1; extra == 'langchain'
Requires-Dist: langchain>=0.1.0; extra == 'langchain'
Provides-Extra: llamaindex
Requires-Dist: llama-index>=0.9.0; extra == 'llamaindex'
Provides-Extra: parsers
Requires-Dist: markdown>=3.5.0; extra == 'parsers'
Requires-Dist: openpyxl>=3.1.0; extra == 'parsers'
Requires-Dist: pypdf>=3.0.0; extra == 'parsers'
Requires-Dist: python-docx>=1.0.0; extra == 'parsers'
Requires-Dist: python-pptx>=0.6.21; extra == 'parsers'
